pyru_env/__init__.py
pyru_env/__main__.py
pyru_env-0.1.1.dist-info/licenses/LICENSE
pyru_env-0.1.1.dist-info/METADATA
pyru_env-0.1.1.dist-info/WHEEL
pyru_env-0.1.1.dist-info/top_level.txt
pyru_env-0.1.1.dist-info/RECORD
