Metadata-Version: 2.4
Name: pyru_env
Version: 0.1.1
Summary: `pyru_env` is a Python module for setting up a combined development environment for Python and Rust
Author-email: Samuel Bjelkemyr <samuel.bjelkemyr@outlook.com>
License-Expression: MIT
Project-URL: Homepage, https://github.com/Radors/pyru_env
Classifier: Programming Language :: Python :: 3
Classifier: Operating System :: OS Independent
Requires-Python: >=3.9
License-File: LICENSE
Dynamic: license-file
